CRUDFilters/__init__.py
CRUDFilters/forms.py
CRUDFilters/manage.py
CRUDFilters/managers.py
CRUDFilters/models.py
CRUDFilters/serializers.py
CRUDFilters/urls.py
CRUDFilters/views.py
CRUDFilters/CRUDFilters/__init__.py
CRUDFilters/CRUDFilters/settings.py
CRUDFilters/CRUDFilters/wsgi.py
CRUDFilters/templates/__init__.py
CRUDFilters/templates/api.html
CRUDFilters/templates/choose_filters.html
CRUDFilters/templates/choose_role.html
CRUDFilters/templatetags/CRUDFilters.py
CRUDFilters/templatetags/__init__.py
CRUDFilters/tests/__init__.py
CRUDFilters/tests/managers.py
CRUDFilters/tests/models.py
CRUDFilters/tests/serializers.py
CRUDFilters/tests/tests.py
CRUDFilters/tests/urls.py
CRUDFilters/tests/views.py
CRUDFilters/tests/migrations/0001_initial.py
CRUDFilters/tests/migrations/__init__.py
crud_filters-0.3.6.dist-info/DESCRIPTION.rst
crud_filters-0.3.6.dist-info/METADATA
crud_filters-0.3.6.dist-info/RECORD
crud_filters-0.3.6.dist-info/WHEEL
crud_filters-0.3.6.dist-info/metadata.json
crud_filters-0.3.6.dist-info/top_level.txt
