Metadata-Version: 2.0
Name: crud-filters
Version: 0.3.6
Summary: django-crud-filters works with django-restframework to provide easily configurable role-based filtering for API endpoints.
Home-page: https://github.com/bellhops/django-crud-filters
Author: Bellhops
Author-email: tech@getbellhops.com
License: UNKNOWN
Download-URL: https://github.com/bellhops/django-crud-filters/dist/crud_filters-0.3.5.tar.gz
Keywords: django,authorization,api,security
Platform: UNKNOWN
Requires-Dist: Django
Requires-Dist: Pillow
Requires-Dist: django-dynamic-fixture
Requires-Dist: djangorestframework
Requires-Dist: djangorestframework-expiring-authtoken
